demo_project_123/__init__.py
demo_project_123/__main__.py
demo_project_123/some_pkg/__init__.py
demo_project_123/some_pkg/some_mod.py
tests/__init__.py
tests/__main__.py
tests/test_sample.py
demo_project_123-0.1.0.dist-info/METADATA
demo_project_123-0.1.0.dist-info/WHEEL
demo_project_123-0.1.0.dist-info/top_level.txt
demo_project_123-0.1.0.dist-info/RECORD
