Metadata-Version: 2.1
Name: demo-project-123
Version: 0.1.0
Summary: A new package.
Home-page: 
Author: John Doe
Author-email: jdoe@t4d.io
License: MIT
